notecard_pseudo_sensor/__init__.py
notecard_pseudo_sensor/notecard_pseudo_sensor.py
notecard_pseudo_sensor-2.0.0.dist-info/LICENSE.mit
notecard_pseudo_sensor-2.0.0.dist-info/METADATA
notecard_pseudo_sensor-2.0.0.dist-info/WHEEL
notecard_pseudo_sensor-2.0.0.dist-info/top_level.txt
notecard_pseudo_sensor-2.0.0.dist-info/RECORD
