Metadata-Version: 2.1
Name: notecard-pseudo-sensor
Version: 2.0.0
Summary: An API interface to the internal sensors of the Blues Wireless Notecard
Home-page: https://github.com/blues/notecard-pseudo-sensor-python
Author: Blues Inc.
Author-email: support@blues.com
License: MIT
Platform: UNKNOWN
Classifier: Programming Language :: Python
Classifier: Programming Language :: Python :: 3.6
Classifier: Programming Language :: Python :: 3.7
Classifier: Programming Language :: Python :: 3.8
Classifier: Programming Language :: Python :: 3.9
Classifier: License :: OSI Approved :: MIT License
Classifier: Operating System :: OS Independent
Classifier: Intended Audience :: Developers
Classifier: Natural Language :: English
Requires-Python: >=3.6
License-File: LICENSE.mit
Requires-Dist: note-python
